vibrant_auth_middleware/__init__.py
vibrant_auth_middleware/config.py
vibrant_auth_middleware/decisions.py
vibrant_auth_middleware/middleware.py
vibrant_auth_middleware/telemetry.py
vibrant_auth_middleware/token_source.py
vibrant_auth_middleware-0.1.1.dist-info/METADATA
vibrant_auth_middleware-0.1.1.dist-info/WHEEL
vibrant_auth_middleware-0.1.1.dist-info/RECORD
