Metadata-Version: 2.4
Name: vibrant-auth-middleware
Version: 0.1.1
Summary: FastAPI middleware for JWT extraction and verification
Project-URL: Homepage, https://github.com/vibrant-auth/middleware
Project-URL: Repository, https://github.com/vibrant-auth/middleware
Project-URL: Issues, https://github.com/vibrant-auth/middleware/issues
Author-email: Tianhao Wang <tianhaowang@example.com>
License: MIT
Keywords: auth,fastapi,jwt,middleware,security
Classifier: Development Status :: 4 - Beta
Classifier: Framework :: FastAPI
Classifier: Intended Audience :: Developers
Classifier: License :: OSI Approved :: MIT License
Classifier: Programming Language :: Python :: 3.13
Classifier: Topic :: Security
Requires-Python: >=3.13
Requires-Dist: fastapi>=0.111
Requires-Dist: pyjwt[crypto]>=2.9
Requires-Dist: pytest-asyncio>=1.2.0
Requires-Dist: pytest>=8.4.2
Requires-Dist: uvicorn>=0.30
Provides-Extra: dev
Requires-Dist: black>=24.8; extra == 'dev'
Requires-Dist: pytest-asyncio>=0.23; extra == 'dev'
Requires-Dist: pytest>=8.3; extra == 'dev'
Requires-Dist: ruff>=0.5; extra == 'dev'
